nose_gevent_monkey.py
nose_gevent_monkey-0.1.0.dist-info/entry_points.txt
nose_gevent_monkey-0.1.0.dist-info/WHEEL
nose_gevent_monkey-0.1.0.dist-info/METADATA
nose_gevent_monkey-0.1.0.dist-info/RECORD
