Metadata-Version: 2.1
Name: nose-gevent-monkey
Version: 0.1.0
Summary: A nose plugin to monkey patch gevent as early as possible
Home-page: UNKNOWN
License: UNKNOWN
Author: BCD Trip Tech
Author-email: development@bcdtriptech.com
Requires-Python: >=3.6,<4.0
Classifier: Programming Language :: Python :: 3
Classifier: Programming Language :: Python :: 3.6
Classifier: Programming Language :: Python :: 3.7
Requires-Dist: nose
